alliance_platform/frontend/__init__.py
alliance_platform/frontend/apps.py
alliance_platform/frontend/bundler/__init__.py
alliance_platform/frontend/bundler/asset_registry.py
alliance_platform/frontend/bundler/base.py
alliance_platform/frontend/bundler/context.py
alliance_platform/frontend/bundler/middleware.py
alliance_platform/frontend/bundler/ssr.py
alliance_platform/frontend/bundler/vanilla_extract.py
alliance_platform/frontend/bundler/vite.py
alliance_platform/frontend/bundler/vitePreload.ts
alliance_platform/frontend/dom_possible_standard_names.py
alliance_platform/frontend/forms/__init__.py
alliance_platform/frontend/forms/renderers.py
alliance_platform/frontend/html_parser.py
alliance_platform/frontend/management/commands/extract_frontend_assets.py
alliance_platform/frontend/prop_handlers.py
alliance_platform/frontend/py.typed
alliance_platform/frontend/settings.py
alliance_platform/frontend/templates/bundler_dev_check.html
alliance_platform/frontend/templatetags/__init__.py
alliance_platform/frontend/templatetags/bundler.py
alliance_platform/frontend/templatetags/react.py
alliance_platform/frontend/templatetags/vanilla_extract.py
alliance_platform/frontend/util.py
alliance_platform_frontend-0.0.21.dist-info/METADATA
alliance_platform_frontend-0.0.21.dist-info/WHEEL
alliance_platform_frontend-0.0.21.dist-info/entry_points.txt
alliance_platform_frontend-0.0.21.dist-info/RECORD
